{
  "last_updated": "2026-07-09T22:17:40.222245",
  "properties": {
    "20_1830": {
      "name": "大井六丁目",
      "ward": "品川区",
      "vacancy_count": 0,
      "url": "https://www.ur-net.go.jp/chintai/kanto/tokyo/20_1830.html",
      "last_changed": "2026-07-09T22:18:01.274602"
    },
    "20_3550": {
      "name": "品川八潮パークタウン 潮路北第二ハイツ",
      "ward": "品川区",
      "vacancy_count": 0,
      "url": "https://www.ur-net.go.jp/chintai/kanto/tokyo/20_3550.html",
      "last_changed": "2026-07-09T22:18:09.127899"
    },
    "20_3640": {
      "name": "品川八潮パークタウン 潮路南第一ハイツ",
      "ward": "品川区",
      "vacancy_count": 0,
      "url": "https://www.ur-net.go.jp/chintai/kanto/tokyo/20_3640.html",
      "last_changed": "2026-07-09T22:18:19.323647"
    },
    "20_3810": {
      "name": "品川八潮パークタウン 潮路中央ハイツ",
      "ward": "品川区",
      "vacancy_count": 0,
      "url": "https://www.ur-net.go.jp/chintai/kanto/tokyo/20_3810.html",
      "last_changed": "2026-07-09T22:18:29.338096"
    },
    "20_7220": {
      "name": "コンフォール品川西大井",
      "ward": "品川区",
      "vacancy_count": 0,
      "url": "https://www.ur-net.go.jp/chintai/kanto/tokyo/20_7220.html",
      "last_changed": "2026-07-09T22:18:43.549156"
    },
    "20_4920": {
      "name": "デュプレ芝浦",
      "ward": "港区",
      "vacancy_count": 0,
      "url": "https://www.ur-net.go.jp/chintai/kanto/tokyo/20_4920.html",
      "last_changed": "2026-07-09T22:18:52.870148"
    },
    "20_5180": {
      "name": "恵比寿ビュータワー",
      "ward": "目黒区",
      "vacancy_count": 0,
      "url": "https://www.ur-net.go.jp/chintai/kanto/tokyo/20_5180.html",
      "last_changed": "2026-07-09T22:19:23.273587"
    },
    "20_6480": {
      "name": "中目黒ゲートタウンハイツ",
      "ward": "目黒区",
      "vacancy_count": 0,
      "url": "https://www.ur-net.go.jp/chintai/kanto/tokyo/20_6480.html",
      "last_changed": "2026-07-09T22:19:33.770934"
    },
    "20_7090": {
      "name": "中目黒アトラスタワー",
      "ward": "目黒区",
      "vacancy_count": 0,
      "url": "https://www.ur-net.go.jp/chintai/kanto/tokyo/20_7090.html",
      "last_changed": "2026-07-09T22:19:41.621896"
    }
  }
}